D_ID.py
did_api-0.0.6.dist-info/LICENSE
did_api-0.0.6.dist-info/METADATA
did_api-0.0.6.dist-info/WHEEL
did_api-0.0.6.dist-info/top_level.txt
did_api-0.0.6.dist-info/RECORD
