Metadata-Version: 2.1
Name: did-api
Version: 0.0.6
Summary: D-ID API Python Library
Home-page: https://github.com/Circuit-Minds/d-id
Author: Shubham Gupta
Author-email: gshubham533@gmail.com
Keywords: D ID API,text to video,t2s,D ID Python library
Classifier: Programming Language :: Python :: 3
Classifier: License :: OSI Approved :: MIT License
Classifier: Operating System :: OS Independent
Requires-Python: >=3.6
License-File: LICENSE
Requires-Dist: requests
